iowarp/__init__.py
iowarp/_installer.py
iowarp/cli.py
iowarp-0.1.1.dist-info/licenses/LICENSE
iowarp-0.1.1.dist-info/METADATA
iowarp-0.1.1.dist-info/WHEEL
iowarp-0.1.1.dist-info/entry_points.txt
iowarp-0.1.1.dist-info/top_level.txt
iowarp-0.1.1.dist-info/RECORD
