Metadata-Version: 2.4
Name: iowarp
Version: 0.1.1
Summary: Unified interface for IOWarp: high-performance I/O runtime and AI agent toolkit
Author: IOWarp Team
License-Expression: BSD-3-Clause
Project-URL: Homepage, https://github.com/iowarp/iowarp
Project-URL: Bug Tracker, https://github.com/iowarp/iowarp/issues
Classifier: Development Status :: 3 - Alpha
Classifier: Intended Audience :: Developers
Classifier: Programming Language :: Python :: 3
Classifier: Programming Language :: Python :: 3.10
Classifier: Programming Language :: Python :: 3.11
Classifier: Programming Language :: Python :: 3.12
Classifier: Programming Language :: Python :: 3.13
Requires-Python: >=3.10
License-File: LICENSE
Requires-Dist: iowarp-agent-toolkit
Requires-Dist: click>=8.1.0
Dynamic: license-file
